polzyFunctions/AntragActivitiesDerive.py
polzyFunctions/AntragActivityRecorder.py
polzyFunctions/ConnectionFactory.py
polzyFunctions/Gamification.py
polzyFunctions/GamificationActivityRecorder.py
polzyFunctions/GlobalConstants.py
polzyFunctions/GlobalSystemConstants.py
polzyFunctions/LogLevelUpdater.py
polzyFunctions/__init__.py
polzyFunctions/Activities/ActivitiesDataClasses.py
polzyFunctions/Activities/Activity.py
polzyFunctions/Activities/AntragActivity.py
polzyFunctions/Activities/LoginActivity.py
polzyFunctions/Activities/__init__.py
polzyFunctions/Dataclasses/Antrag.py
polzyFunctions/Dataclasses/AntragsStatus.py
polzyFunctions/Dataclasses/CommonFieldnames.py
polzyFunctions/Dataclasses/FieldCatalogManager.py
polzyFunctions/Dataclasses/PersonRoles.py
polzyFunctions/Dataclasses/__init__.py
polzyFunctions/polzyvig/__init__.py
polzyFunctions/polzyvig/antrag.py
polzyFunctions/scripts/AddNotification.py
polzyFunctions/scripts/Excel2Json.py
polzyFunctions/scripts/ExcelDBManager.py
polzyFunctions/scripts/GamificationStatsUpdater.py
polzyFunctions/scripts/__init__.py
polzyFunctions/scripts/config.py
polzyFunctions/scripts/utils.py
polzyFunctions/translator/DataHandler.py
polzyFunctions/translator/ManageTranslations.py
polzyFunctions/translator/__init__.py
polzyFunctions/utils/__init__.py
polzyFunctions/utils/counter.py
polzybackend/GamificationHandler.py
polzybackend/__init__.py
polzybackend/mediators.py
polzybackend/messenger.py
polzybackend/models.py
polzybackend/administration/__init__.py
polzybackend/administration/routes.py
polzybackend/announce/__init__.py
polzybackend/announce/routes.py
polzybackend/antrag/__init__.py
polzybackend/antrag/routes.py
polzybackend/authenticate/__init__.py
polzybackend/authenticate/routes.py
polzybackend/debug/__init__.py
polzybackend/debug/routes.py
polzybackend/gamification/__init__.py
polzybackend/gamification/routes.py
polzybackend/general/__init__.py
polzybackend/general/routes.py
polzybackend/policy/__init__.py
polzybackend-1.0.0.dist-info/LICENSE
polzybackend-1.0.0.dist-info/METADATA
polzybackend-1.0.0.dist-info/WHEEL
polzybackend-1.0.0.dist-info/top_level.txt
polzybackend-1.0.0.dist-info/RECORD
