Metadata-Version: 2.1
Name: polzybackend
Version: 1.0.0
Summary: Open source Insurance Policy Life Cycle Management
Home-page: https://baangt.org
Author: Bernhard Buhl
Author-email: buhl@buhl-consulting.com.cy
License: UNKNOWN
Platform: UNKNOWN
Classifier: Programming Language :: Python :: 3
Classifier: License :: OSI Approved :: MIT License
Classifier: Operating System :: OS Independent
Requires-Python: >=3.6
Requires-Dist: alembic (==1.4.3)
Requires-Dist: certifi (==2020.6.20)
Requires-Dist: chardet (==3.0.4)
Requires-Dist: click (==7.1.2)
Requires-Dist: Flask (==1.1.2)
Requires-Dist: Flask-HTTPAuth (==4.1.0)
Requires-Dist: Flask-Migrate (==2.5.3)
Requires-Dist: Flask-SQLAlchemy (==2.5.1)
Requires-Dist: flask-monitoringdashboard (>=3.1.0)
Requires-Dist: idna (==2.10)
Requires-Dist: itsdangerous (==1.1.0)
Requires-Dist: Jinja2 (>=2.11.1)
Requires-Dist: Mako (==1.1.3)
Requires-Dist: MarkupSafe (==1.1.1)
Requires-Dist: python-dateutil (==2.8.1)
Requires-Dist: python-editor (==1.0.4)
Requires-Dist: requests (>=2.24.0)
Requires-Dist: six (>=1.15.0)
Requires-Dist: SQLAlchemy (>=1.4.9)
Requires-Dist: urllib3 (>=1.25.10)
Requires-Dist: Werkzeug (>=1.0.1)
Requires-Dist: Flask-Cors (>=3.0.10)
